queueup/__init__.py
queueup/_queue.py
queueup-0.1.dist-info/METADATA
queueup-0.1.dist-info/WHEEL
queueup-0.1.dist-info/top_level.txt
queueup-0.1.dist-info/RECORD
