Metadata-Version: 2.1
Name: queueup
Version: 0.1
Summary: A distributed queue library layered over kombu
Home-page: UNKNOWN
Author: Kevin Hill
Author-email: kah.kevin.hill@gmail.com
License: UNKNOWN
Platform: UNKNOWN
Classifier: Programming Language :: Python :: 3
Classifier: License :: OSI Approved :: MIT License
Classifier: Operating System :: OS Independent
Requires-Dist: kombu
Requires-Dist: arangodb
Requires-Dist: auth
Requires-Dist: brotli
Requires-Dist: eventlet
Requires-Dist: gevent
Requires-Dist: librabbitmq
Requires-Dist: pymongo
Requires-Dist: msgpack
Requires-Dist: redis
Requires-Dist: sqlalchemy
